simpleor/__init__.py
simpleor/base.py
simpleor/cli.py
simpleor/matchmaker.py
simpleor/monitoring.py
simpleor/scheduler.py
simpleor/utils.py
simpleor-0.0.13.dist-info/AUTHORS.rst
simpleor-0.0.13.dist-info/LICENSE
simpleor-0.0.13.dist-info/METADATA
simpleor-0.0.13.dist-info/WHEEL
simpleor-0.0.13.dist-info/entry_points.txt
simpleor-0.0.13.dist-info/top_level.txt
simpleor-0.0.13.dist-info/RECORD
