Metadata-Version: 2.1
Name: simpleor
Version: 0.0.13
Summary: Package to solve Operations Research problems.
Home-page: https://github.com/simple-ai-opensource/simple-or
Author: Lennart Damen
Author-email: lennart.damen.ai@gmail.com
License: GNU General Public License v3
Keywords: simpleor
Platform: UNKNOWN
Classifier: Development Status :: 2 - Pre-Alpha
Classifier: Intended Audience :: Developers
Classifier: License :: OSI Approved :: GNU General Public License v3 (GPLv3)
Classifier: Natural Language :: English
Classifier: Programming Language :: Python :: 3.7
Classifier: Programming Language :: Python :: 3.8
Requires-Python: >=3.7
Requires-Dist: Click (>=7.0)
Requires-Dist: numpy
Requires-Dist: pulp
Requires-Dist: pandas
Provides-Extra: dev
Requires-Dist: pytest (>=3) ; extra == 'dev'
Requires-Dist: pytest-cov ; extra == 'dev'
Requires-Dist: black ; extra == 'dev'
Requires-Dist: flake8 ; extra == 'dev'
Requires-Dist: pre-commit ; extra == 'dev'
Requires-Dist: mypy ; extra == 'dev'
Requires-Dist: isort ; extra == 'dev'
Requires-Dist: bump2version ; extra == 'dev'
Provides-Extra: docs
Requires-Dist: sphinx ; extra == 'docs'
Requires-Dist: sphinx-panels ; extra == 'docs'
Provides-Extra: test
Requires-Dist: pytest (>=3) ; extra == 'test'
Requires-Dist: pytest-cov ; extra == 'test'
